setup.py
redis_logging_handler/__init__.py
redis_logging_handler/handler.py
redis_logging_handler/handler_test.py
redis_logging_handler.egg-info/PKG-INFO
redis_logging_handler.egg-info/SOURCES.txt
redis_logging_handler.egg-info/dependency_links.txt
redis_logging_handler.egg-info/requires.txt
redis_logging_handler.egg-info/top_level.txt