Metadata-Version: 1.0
Name: redis-logging-handler
Version: 0.1
Summary: a redis log handler
Home-page: UNKNOWN
Author: DrWrong
Author-email: yuhangchaney@gmail.com
License: UNKNOWN
Platform: UNKNOWN
